sokrates/__init__.py
sokrates/colors.py
sokrates/config.py
sokrates/constants.py
sokrates/file_helper.py
sokrates/llm_api.py
sokrates/output_printer.py
sokrates/prompt_constructor.py
sokrates/prompt_refiner.py
sokrates/system_monitor.py
sokrates/text_to_speech.py
sokrates/utils.py
sokrates/voice_helper.py
sokrates/cli/__init__.py
sokrates/cli/helper.py
sokrates/cli/sokrates_benchmark_model.py
sokrates/cli/sokrates_benchmark_results_merger.py
sokrates/cli/sokrates_benchmark_results_to_markdown.py
sokrates/cli/sokrates_breakdown_task.py
sokrates/cli/sokrates_chat.py
sokrates/cli/sokrates_execute_tasks.py
sokrates/cli/sokrates_fetch_to_md.py
sokrates/cli/sokrates_generate_mantra.py
sokrates/cli/sokrates_idea_generator.py
sokrates/cli/sokrates_list_models.py
sokrates/cli/sokrates_merge_ideas.py
sokrates/cli/sokrates_refine_and_send_prompt.py
sokrates/cli/sokrates_refine_prompt.py
sokrates/cli/sokrates_send_prompt.py
sokrates/cli/coding/sokrates_code_analyze.py
sokrates/cli/coding/sokrates_code_generate_tests.py
sokrates/cli/coding/sokrates_code_review.py
sokrates/cli/coding/sokrates_code_summarize.py
sokrates/cli/task_queue/__init__.py
sokrates/cli/task_queue/sokrates_daemon.py
sokrates/cli/task_queue/sokrates_task_add.py
sokrates/cli/task_queue/sokrates_task_list.py
sokrates/cli/task_queue/sokrates_task_remove.py
sokrates/cli/task_queue/sokrates_task_status.py
sokrates/coding/__init__.py
sokrates/coding/analyze_repository_workflow.py
sokrates/coding/code_review_workflow.py
sokrates/coding/python_analyzer.py
sokrates/coding/test_generator.py
sokrates/prompts/breakdown-v1.md
sokrates/prompts/generate-mantra-v1.md
sokrates/prompts/german-v1.md
sokrates/prompts/merge-ideas-v1.md
sokrates/prompts/refine-coding-v2.md
sokrates/prompts/refine-coding-v3.md
sokrates/prompts/refine-coding.md
sokrates/prompts/refine-concept.md
sokrates/prompts/refine-prd.md
sokrates/prompts/refine-prompt.md
sokrates/prompts/coding/analyze_repository.md
sokrates-0.11.0.dist-info/licenses/LICENSE
sokrates-0.11.0.dist-info/METADATA
sokrates-0.11.0.dist-info/WHEEL
sokrates-0.11.0.dist-info/entry_points.txt
sokrates-0.11.0.dist-info/top_level.txt
sokrates-0.11.0.dist-info/RECORD
