Metadata-Version: 2.4
Name: sokrates
Version: 0.11.0
Summary: A collection of tools for LLM interactions like prompt refinement and idea generation. It also provides a console chat client with speech to text feature.
Author-email: Julian Weber <julianweberdev@gmail.com>
License: MIT License
Project-URL: Homepage, https://github.com/Kubementat/sokrates
Project-URL: Repository, https://github.com/Kubementat/sokrates
Keywords: llm,tools,system-monitoring,ai,prompt refinement,idea generation
Classifier: Programming Language :: Python :: 3
Classifier: License :: OSI Approved :: MIT License
Classifier: Operating System :: OS Independent
Requires-Python: >=3.9
License-File: LICENSE
Requires-Dist: openai
Requires-Dist: psutil
Requires-Dist: requests
Requires-Dist: markdownify
Requires-Dist: tabulate
Requires-Dist: colorama
Requires-Dist: html2text
Requires-Dist: dotenv
Requires-Dist: watchdog
Provides-Extra: voice
Requires-Dist: openai-whisper>=2023.10.1; extra == "voice"
Requires-Dist: TTS>=0.12.0; extra == "voice"
Requires-Dist: numpy>=1.22.0; extra == "voice"
Requires-Dist: pyaudio; extra == "voice"
Provides-Extra: dev
Requires-Dist: pytest; extra == "dev"
Requires-Dist: pytest-mock; extra == "dev"
Requires-Dist: pytest-cov; extra == "dev"
Requires-Dist: ruff; extra == "dev"
Dynamic: license-file
